LICENSE
ruia_peewee_async/__init__.py
ruia_peewee_async-1.3.3.dist-info/LICENSE
ruia_peewee_async-1.3.3.dist-info/WHEEL
ruia_peewee_async-1.3.3.dist-info/METADATA
ruia_peewee_async-1.3.3.dist-info/RECORD
